<?xml version="1.0" encoding="UTF-8" standalone="no"?>
<job xmlns="urn:proactive:jobdescriptor:3.12" xmlns:xsi="http://www.w3.org/2001/XMLSchema-instance" maxNumberOfExecution="2" name="In_Memory_Iris_Flowers_Classification" onTaskError="continueJobExecution" priority="normal" projectName="5. In Memory Workflows" xsi:schemaLocation="urn:proactive:jobdescriptor:3.12 http://www.activeeon.com/public_content/schemas/proactive/jobdescriptor/3.12/schedulerjob.xsd">
  <variables>
    <variable model="PA:LIST(python3,/usr/bin/python3,/home/proactive/anaconda3/bin/python)" name="PYTHON_COMMAND" value="/home/proactive/anaconda3/bin/python"/>
    <variable model="PA:Boolean" name="IPYPARALLEL_ENABLED" value="True"/>
    <variable model="PA:Integer" name="IPYPARALLEL_ENGINE" value="0"/>
    <variable name="IPYPARALLEL_CONNECTOR" value=""/>
    <variable model="PA:Boolean" name="DOCKER_ENABLED" value="False"/>
    <variable model="PA:LIST(,GPU)" name="NODE_ACCESS_TOKEN" value="GPU"/>
  </variables>
  <description>
    <![CDATA[ Classify Iris flowers using an external IPython Engine for in-memory execution. ]]>
  </description>
  <genericInformation>
<info name="bucketName" value="machine-learning-workflows"/>
<info name="workflow.icon" value="/automation-dashboard/styles/patterns/img/wf-icons/machine_learning.png"/>
<info name="PYTHON_COMMAND" value="$PYTHON_COMMAND"/>
<info name="IPYPARALLEL_ENABLED" value="$IPYPARALLEL_ENABLED"/>
<info name="Documentation" value="PML/PMLUserGuide.html#_in_memory_workflows"/>
<info name="NODE_ACCESS_TOKEN" value="$NODE_ACCESS_TOKEN"/>
<info name="IPYPARALLEL_ENGINE" value="$IPYPARALLEL_ENGINE"/>
<info name="IPYPARALLEL_CONNECTOR" value="$IPYPARALLEL_CONNECTOR"/>
<info name="group" value="public-objects"/>
</genericInformation>
  <taskFlow>
    <task fork="true" name="Load_Iris_Dataset" preciousResult="true">
      <description>
        <![CDATA[ Load and return the iris dataset classification. ]]>
      </description>
      <variables>
        <variable inherited="true" model="PA:Boolean" name="DOCKER_ENABLED" value="True"/>
        <variable inherited="true" name="DOCKER_IMAGE" value="activeeon/dlm3"/>
        <variable inherited="false" model="PA:Boolean" name="TASK_ENABLED" value="True"/>
        <variable inherited="false" model="PA:LIST(PA:URL,PA:URI,PA:USER_FILE,PA:GLOBAL_FILE)" name="IMPORT_FROM" value="PA:URL"/>
        <variable inherited="false" model="$IMPORT_FROM" name="FILE_PATH" value="https://s3.eu-west-2.amazonaws.com/activeeon-public/datasets/iris.csv"/>
        <variable inherited="false" name="FILE_DELIMITER" value=","/>
        <variable inherited="false" model="PA:Integer" name="LIMIT_OUTPUT_VIEW" value="-1"/>
      </variables>
      <genericInformation>
        <info name="task.icon" value="/automation-dashboard/styles/patterns/img/wf-icons/load_dataset.png"/>
        <info name="task.documentation" value="PML/PMLUserGuide.html#_load_iris_dataset"/>
      </genericInformation>
      <forkEnvironment javaHome="/usr">
        <envScript>
          <script>
            <file language="groovy" url="${PA_CATALOG_REST_URL}/buckets/scripts/resources/fork_env_docker_vars/raw"/>
          </script>
        </envScript>
      </forkEnvironment>
      <scriptExecutable>
        <script>
          <file language="cpython" url="${PA_CATALOG_REST_URL}/buckets/machine-learning/resources/Load_Iris_Dataset_Script/raw"/>
        </script>
      </scriptExecutable>
      <controlFlow block="none"/>
      <metadata>
        <positionTop>
            512.953125
        </positionTop>
        <positionLeft>
            226.046875
        </positionLeft>
      </metadata>
    </task>
    <task fork="true" name="Split_Data">
      <description>
        <![CDATA[ Separate data into training and testing sets. ]]>
      </description>
      <variables>
        <variable inherited="false" name="TRAIN_SIZE" value="0.7"/>
        <variable inherited="true" model="PA:Boolean" name="DOCKER_ENABLED" value="True"/>
        <variable inherited="true" name="DOCKER_IMAGE" value="activeeon/dlm3"/>
        <variable inherited="false" model="PA:Boolean" name="TASK_ENABLED" value="True"/>
      </variables>
      <genericInformation>
        <info name="task.icon" value="/automation-dashboard/styles/patterns/img/wf-icons/data-processing.png"/>
        <info name="task.documentation" value="PML/PMLUserGuide.html#_split_data"/>
      </genericInformation>
      <depends>
        <task ref="Load_Iris_Dataset"/>
      </depends>
      <forkEnvironment javaHome="/usr">
        <envScript>
          <script>
            <file language="groovy" url="${PA_CATALOG_REST_URL}/buckets/scripts/resources/fork_env_docker_vars/raw"/>
          </script>
        </envScript>
      </forkEnvironment>
      <scriptExecutable>
        <script>
          <file language="cpython" url="${PA_CATALOG_REST_URL}/buckets/machine-learning/resources/Split_Data_Script/raw"/>
        </script>
      </scriptExecutable>
      <controlFlow block="none"/>
      <metadata>
        <positionTop>
            640.953125
        </positionTop>
        <positionLeft>
            226.046875
        </positionLeft>
      </metadata>
    </task>
    <task fork="true" name="Download_Model" preciousResult="true">
      <description>
        <![CDATA[ Download a trained model. ]]>
      </description>
      <variables>
        <variable inherited="true" model="PA:Boolean" name="DOCKER_ENABLED" value="True"/>
        <variable inherited="true" name="DOCKER_IMAGE" value="activeeon/dlm3"/>
        <variable inherited="false" model="PA:Boolean" name="TASK_ENABLED" value="True"/>
      </variables>
      <genericInformation>
        <info name="task.icon" value="/automation-dashboard/styles/patterns/img/wf-icons/download_model.png"/>
        <info name="task.documentation" value="PML/PMLUserGuide.html#_download_model"/>
      </genericInformation>
      <depends>
        <task ref="Train_Model"/>
      </depends>
      <forkEnvironment javaHome="/usr">
        <envScript>
          <script>
            <file language="groovy" url="${PA_CATALOG_REST_URL}/buckets/scripts/resources/fork_env_docker_vars/raw"/>
          </script>
        </envScript>
      </forkEnvironment>
      <scriptExecutable>
        <script>
          <file language="cpython" url="${PA_CATALOG_REST_URL}/buckets/machine-learning/resources/Download_Model_Script/raw"/>
        </script>
      </scriptExecutable>
      <controlFlow block="none"/>
      <metadata>
        <positionTop>
            896.953125
        </positionTop>
        <positionLeft>
            226.046875
        </positionLeft>
      </metadata>
    </task>
    <task fork="true" name="Predict_Model" preciousResult="true">
      <description>
        <![CDATA[ Generate predictions using a trained model. ]]>
      </description>
      <variables>
        <variable inherited="true" model="PA:Boolean" name="DOCKER_ENABLED" value="True"/>
        <variable inherited="true" name="DOCKER_IMAGE" value="activeeon/dlm3"/>
        <variable inherited="false" model="PA:Boolean" name="TASK_ENABLED" value="True"/>
        <variable inherited="false" name="LABEL_COLUMN" value=""/>
      </variables>
      <genericInformation>
        <info name="task.icon" value="/automation-dashboard/styles/patterns/img/wf-icons/predict.png"/>
        <info name="task.documentation" value="PML/PMLUserGuide.html#_predict_model"/>
      </genericInformation>
      <depends>
        <task ref="Split_Data"/>
        <task ref="Train_Model"/>
      </depends>
      <forkEnvironment javaHome="/usr">
        <envScript>
          <script>
            <file language="groovy" url="${PA_CATALOG_REST_URL}/buckets/scripts/resources/fork_env_docker_vars/raw"/>
          </script>
        </envScript>
      </forkEnvironment>
      <scriptExecutable>
        <script>
          <file language="cpython" url="${PA_CATALOG_REST_URL}/buckets/machine-learning/resources/Predict_Model_Script/raw"/>
        </script>
      </scriptExecutable>
      <controlFlow block="none"/>
      <metadata>
        <positionTop>
            897.953125
        </positionTop>
        <positionLeft>
            354.046875
        </positionLeft>
      </metadata>
    </task>
    <task fork="true" name="Preview_Results" preciousResult="true">
      <description>
        <![CDATA[ Preview the HTML results of the predictions. ]]>
      </description>
      <variables>
        <variable inherited="true" model="PA:Boolean" name="DOCKER_ENABLED" value="True"/>
        <variable inherited="true" name="DOCKER_IMAGE" value="activeeon/dlm3"/>
        <variable inherited="false" model="PA:Boolean" name="TASK_ENABLED" value="True"/>
        <variable inherited="false" model="PA:LIST(CSV,JSON,HTML)" name="OUTPUT_TYPE" value="HTML"/>
        <variable inherited="false" model="PA:Integer" name="LIMIT_OUTPUT_VIEW" value="1000"/>
      </variables>
      <genericInformation>
        <info name="task.icon" value="/automation-dashboard/styles/patterns/img/wf-icons/preview_results.png"/>
        <info name="task.documentation" value="PML/PMLUserGuide.html#_preview_results"/>
      </genericInformation>
      <depends>
        <task ref="Predict_Model"/>
      </depends>
      <forkEnvironment javaHome="/usr">
        <envScript>
          <script>
            <file language="groovy" url="${PA_CATALOG_REST_URL}/buckets/scripts/resources/fork_env_docker_vars/raw"/>
          </script>
        </envScript>
      </forkEnvironment>
      <scriptExecutable>
        <script>
          <file language="cpython" url="${PA_CATALOG_REST_URL}/buckets/machine-learning/resources/Preview_Results_Script/raw"/>
        </script>
      </scriptExecutable>
      <controlFlow block="none"/>
      <metadata>
        <positionTop>
            1024.953125
        </positionTop>
        <positionLeft>
            354.046875
        </positionLeft>
      </metadata>
    </task>
    <task fork="true" name="Logistic_Regression">
      <description>
        <![CDATA[ Logistic Regression is a regression model where the Dependent Variable (DV) is categorical. ]]>
      </description>
      <variables>
        <variable inherited="true" model="PA:Boolean" name="DOCKER_ENABLED" value="True"/>
        <variable inherited="true" name="DOCKER_IMAGE" value="activeeon/dlm3"/>
        <variable inherited="false" model="PA:Boolean" name="TASK_ENABLED" value="True"/>
        <variable inherited="true" name="INPUT_VARIABLES" value="{}"/>
        <variable inherited="false" model="PA:List(accuracy,balanced_accuracy, average_precision, brier_score_loss, f1, f1_micro, f1_macro, f1_weighted, f1_samples, neg_log_loss, precision, recall, roc_auc)" name="SCORING" value="accuracy"/>
      </variables>
      <genericInformation>
        <info name="task.icon" value="/automation-dashboard/styles/patterns/img/wf-icons/ml_classification.png"/>
        <info name="task.documentation" value="PML/PMLUserGuide.html#_logistic_regression"/>
      </genericInformation>
      <forkEnvironment javaHome="/usr">
        <envScript>
          <script>
            <file language="groovy" url="${PA_CATALOG_REST_URL}/buckets/scripts/resources/fork_env_docker_vars/raw"/>
          </script>
        </envScript>
      </forkEnvironment>
      <pre>
        <script>
          <file language="groovy" url="${PA_CATALOG_REST_URL}/buckets/auto-ml-optimization/resources/get_automl_params/raw"/>
        </script>
      </pre>
      <scriptExecutable>
        <script>
          <file language="cpython" url="${PA_CATALOG_REST_URL}/buckets/machine-learning/resources/Logistic_Regression_Script/raw"/>
        </script>
      </scriptExecutable>
      <controlFlow block="none"/>
      <metadata>
        <positionTop>
            640.953125
        </positionTop>
        <positionLeft>
            354.046875
        </positionLeft>
      </metadata>
    </task>
    <task fork="true" name="Train_Model">
      <description>
        <![CDATA[ Train a classification/clustering/anomaly detection model. ]]>
      </description>
      <variables>
        <variable inherited="true" name="DOCKER_ENABLED" value="True"/>
        <variable inherited="true" name="DOCKER_IMAGE" value="activeeon/dlm3"/>
        <variable inherited="false" name="TASK_ENABLED" value="True"/>
        <variable inherited="false" name="LABEL_COLUMN" value="species"/>
        <variable inherited="false" model="PA:Integer" name="N_SPLITS" value="5"/>
      </variables>
      <genericInformation>
        <info name="task.icon" value="/automation-dashboard/styles/patterns/img/wf-icons/train.png"/>
        <info name="task.documentation" value="PML/PMLUserGuide.html#_train_model"/>
      </genericInformation>
      <depends>
        <task ref="Split_Data"/>
        <task ref="Logistic_Regression"/>
      </depends>
      <forkEnvironment javaHome="/usr">
        <envScript>
          <script>
            <file language="groovy" url="${PA_CATALOG_REST_URL}/buckets/scripts/resources/fork_env_docker_vars/raw"/>
          </script>
        </envScript>
      </forkEnvironment>
      <pre>
        <script>
          <file language="groovy" url="${PA_CATALOG_REST_URL}/buckets/auto-ml-optimization/resources/get_automl_token/raw"/>
        </script>
      </pre>
      <scriptExecutable>
        <script>
          <file language="cpython" url="${PA_CATALOG_REST_URL}/buckets/machine-learning/resources/Train_Model_Script/raw"/>
        </script>
      </scriptExecutable>
      <controlFlow block="none"/>
      <metadata>
        <positionTop>
            768.953125
        </positionTop>
        <positionLeft>
            354.046875
        </positionLeft>
      </metadata>
    </task>
  </taskFlow>
  <metadata>
    <visualization>
      <![CDATA[ <html>
    <head>
    <link rel="stylesheet" href="/studio/styles/studio-standalone.css">
        <style>
        #workflow-designer {
            left:0 !important;
            top:0 !important;
            width:2144px;
            height:2420px;
            }
        </style>
    </head>
    <body>
    <div id="workflow-visualization-view"><div id="workflow-visualization" style="position:relative;top:-507.953125px;left:-221.046875px"><div class="task _jsPlumb_endpoint_anchor_ ui-draggable" id="jsPlumb_1_168" style="top: 512.953px; left: 226.047px;"><a class="task-name" data-toggle="tooltip" data-placement="right" title="Load and return the iris dataset classification."><img src="/automation-dashboard/styles/patterns/img/wf-icons/load_dataset.png" width="20px">&nbsp;<span class="name">Load_Iris_Dataset</span></a></div><div class="task ui-draggable _jsPlumb_endpoint_anchor_" id="jsPlumb_1_171" style="top: 640.953px; left: 226.047px;"><a class="task-name" data-toggle="tooltip" data-placement="right" title="Separate data into training and testing sets."><img src="/automation-dashboard/styles/patterns/img/wf-icons/data-processing.png" width="20px">&nbsp;<span class="name">Split_Data</span></a></div><div class="task ui-draggable _jsPlumb_endpoint_anchor_" id="jsPlumb_1_174" style="top: 896.953px; left: 226.047px;"><a class="task-name" data-toggle="tooltip" data-placement="right" title="Download a trained model."><img src="/automation-dashboard/styles/patterns/img/wf-icons/download_model.png" width="20px">&nbsp;<span class="name">Download_Model</span></a></div><div class="task ui-draggable _jsPlumb_endpoint_anchor_" id="jsPlumb_1_177" style="top: 897.953px; left: 354.047px; z-index: 24;"><a class="task-name" data-toggle="tooltip" data-placement="right" title="Generate predictions using a trained model."><img src="/automation-dashboard/styles/patterns/img/wf-icons/predict.png" width="20px">&nbsp;<span class="name">Predict_Model</span></a></div><div class="task ui-draggable _jsPlumb_endpoint_anchor_" id="jsPlumb_1_180" style="top: 1024.95px; left: 354.047px;"><a class="task-name" data-toggle="tooltip" data-placement="right" title="Preview the HTML results of the predictions."><img src="/automation-dashboard/styles/patterns/img/wf-icons/preview_results.png" width="20px">&nbsp;<span class="name">Preview_Results</span></a></div><div class="task _jsPlumb_endpoint_anchor_ ui-draggable" id="jsPlumb_1_183" style="top: 640.953px; left: 354.047px;"><a class="task-name" data-toggle="tooltip" data-placement="right" title="Logistic Regression is a regression model where the Dependent Variable (DV) is categorical."><img src="/automation-dashboard/styles/patterns/img/wf-icons/ml_classification.png" width="20px">&nbsp;<span class="name">Logistic_Regression</span></a></div><div class="task ui-draggable _jsPlumb_endpoint_anchor_" id="jsPlumb_1_186" style="top: 768.953px; left: 354.047px;"><a class="task-name" data-toggle="tooltip" data-placement="right" title="Train a classification/clustering/anomaly detection model."><img src="/automation-dashboard/styles/patterns/img/wf-icons/train.png" width="20px">&nbsp;<span class="name">Train_Model</span></a></div><svg style="position:absolute;left:265.5px;top:552.5px" width="29" height="89" pointer-events="none" position="absolute" version="1.1" xmlns="http://www.w3.org/1999/xhtml" class="_jsPlumb_connector "><path d="M 0 88 C -10 38 18 50 8 0 " transform="translate(10.5,0.5)" pointer-events="visibleStroke" version="1.1" xmlns="http://www.w3.org/1999/xhtml" fill="none" stroke="#666" style=""></path><path pointer-events="all" version="1.1" xmlns="http://www.w3.org/1999/xhtml" d="M-2.149632,66.303232 L7.49984351657956,47.438247975227235 L-0.24966605297428535,52.43275510120006 L-6.370633382220376,45.538282028201515 L-2.149632,66.303232" class="" stroke="#666" fill="#666" transform="translate(10.5,0.5)"></path><path pointer-events="all" version="1.1" xmlns="http://www.w3.org/1999/xhtml" d="M-2.149632,66.303232 L7.49984351657956,47.438247975227235 L-0.24966605297428535,52.43275510120006 L-6.370633382220376,45.538282028201515 L-2.149632,66.303232" class="" stroke="#666" fill="#666" transform="translate(10.5,0.5)"></path></svg><svg style="position:absolute;left:271.5px;top:808.5px" width="143" height="89" pointer-events="none" position="absolute" version="1.1" xmlns="http://www.w3.org/1999/xhtml" class="_jsPlumb_connector"><path d="M 0 88 C -10 38 132 50 122 0 " transform="translate(10.5,0.5)" pointer-events="visibleStroke" version="1.1" xmlns="http://www.w3.org/1999/xhtml" fill="none" stroke="#666" style=""></path><path pointer-events="all" version="1.1" xmlns="http://www.w3.org/1999/xhtml" d="M14.863103999999998,60.999424000000005 L35.851621418405045,58.08701321556247 L27.316040793493393,54.60220857317104 L29.45440599157608,45.63407642206908 L14.863103999999998,60.999424000000005" class="" stroke="#666" fill="#666" transform="translate(10.5,0.5)"></path><path pointer-events="all" version="1.1" xmlns="http://www.w3.org/1999/xhtml" d="M14.863103999999998,60.999424000000005 L35.851621418405045,58.08701321556247 L27.316040793493393,54.60220857317104 L29.45440599157608,45.63407642206908 L14.863103999999998,60.999424000000005" class="" stroke="#666" fill="#666" transform="translate(10.5,0.5)"></path></svg><svg style="position:absolute;left:265.5px;top:680.5px" width="149.046875" height="217.953125" pointer-events="none" position="absolute" version="1.1" xmlns="http://www.w3.org/1999/xhtml" class="_jsPlumb_connector"><path d="M 128.046875 216.953125 C 138.046875 166.953125 -10 50 0 0 " transform="translate(10.5,0.5)" pointer-events="visibleStroke" version="1.1" xmlns="http://www.w3.org/1999/xhtml" fill="none" stroke="#666" style=""></path><path pointer-events="all" version="1.1" xmlns="http://www.w3.org/1999/xhtml" d="M109.35063249999999,166.7285675 L103.65198770888767,146.31961241786195 L101.34239610899559,155.2451816793549 L92.16860188824259,154.32784880886635 L109.35063249999999,166.7285675" class="" stroke="#666" fill="#666" transform="translate(10.5,0.5)"></path><path pointer-events="all" version="1.1" xmlns="http://www.w3.org/1999/xhtml" d="M109.35063249999999,166.7285675 L103.65198770888767,146.31961241786195 L101.34239610899559,155.2451816793549 L92.16860188824259,154.32784880886635 L109.35063249999999,166.7285675" class="" stroke="#666" fill="#666" transform="translate(10.5,0.5)"></path></svg><svg style="position:absolute;left:393.5px;top:808.5px" width="21.046875" height="89.953125" pointer-events="none" position="absolute" version="1.1" xmlns="http://www.w3.org/1999/xhtml" class="_jsPlumb_connector"><path d="M 0.046875 88.953125 C 10.046875 38.953125 -10 50 0 0 " transform="translate(10.5,0.5)" pointer-events="visibleStroke" version="1.1" xmlns="http://www.w3.org/1999/xhtml" fill="none" stroke="#666" style=""></path><path pointer-events="all" version="1.1" xmlns="http://www.w3.org/1999/xhtml" d="M2.8767854999999996,67.1748305 L9.235751189626864,46.96187536330244 L2.4305511786172844,53.18194391679566 L-4.757135393577479,47.40810968468516 L2.8767854999999996,67.1748305" class="" stroke="#666" fill="#666" transform="translate(10.5,0.5)"></path><path pointer-events="all" version="1.1" xmlns="http://www.w3.org/1999/xhtml" d="M2.8767854999999996,67.1748305 L9.235751189626864,46.96187536330244 L2.4305511786172844,53.18194391679566 L-4.757135393577479,47.40810968468516 L2.8767854999999996,67.1748305" class="" stroke="#666" fill="#666" transform="translate(10.5,0.5)"></path></svg><svg style="position:absolute;left:393.546875px;top:937.453125px" width="25.453125" height="88.046875" pointer-events="none" position="absolute" version="1.1" xmlns="http://www.w3.org/1999/xhtml" class="_jsPlumb_connector"><path d="M 4.453125 87.046875 C 14.453125 37.046875 -10 50 0 0 " transform="translate(10.5,0.5)" pointer-events="visibleStroke" version="1.1" xmlns="http://www.w3.org/1999/xhtml" fill="none" stroke="#666" style=""></path><path pointer-events="all" version="1.1" xmlns="http://www.w3.org/1999/xhtml" d="M6.907038574218749,65.90591455078126 L12.141153189308278,45.37291564180291 L5.6894844520476795,51.95895925725629 L-1.8058021042166938,46.59046976397398 L6.907038574218749,65.90591455078126" class="" stroke="#666" fill="#666" transform="translate(10.5,0.5)"></path><path pointer-events="all" version="1.1" xmlns="http://www.w3.org/1999/xhtml" d="M6.907038574218749,65.90591455078126 L12.141153189308278,45.37291564180291 L5.6894844520476795,51.95895925725629 L-1.8058021042166938,46.59046976397398 L6.907038574218749,65.90591455078126" class="" stroke="#666" fill="#666" transform="translate(10.5,0.5)"></path></svg><svg style="position:absolute;left:265.5px;top:680.5px" width="149" height="89" pointer-events="none" position="absolute" version="1.1" xmlns="http://www.w3.org/1999/xhtml" class="_jsPlumb_connector"><path d="M 128 88 C 138 38 -10 50 0 0 " transform="translate(10.5,0.5)" pointer-events="visibleStroke" version="1.1" xmlns="http://www.w3.org/1999/xhtml" fill="none" stroke="#666" style=""></path><path pointer-events="all" version="1.1" xmlns="http://www.w3.org/1999/xhtml" d="M112.265984,60.999424000000005 L97.39194630220584,45.90760493917774 L99.69643205491549,54.834493838204 L91.22701614040983,58.47715688426225 L112.265984,60.999424000000005" class="" stroke="#666" fill="#666" transform="translate(10.5,0.5)"></path><path pointer-events="all" version="1.1" xmlns="http://www.w3.org/1999/xhtml" d="M112.265984,60.999424000000005 L97.39194630220584,45.90760493917774 L99.69643205491549,54.834493838204 L91.22701614040983,58.47715688426225 L112.265984,60.999424000000005" class="" stroke="#666" fill="#666" transform="translate(10.5,0.5)"></path></svg><svg style="position:absolute;left:393.5px;top:680.5px" width="33.5" height="89" pointer-events="none" position="absolute" version="1.1" xmlns="http://www.w3.org/1999/xhtml" class="_jsPlumb_connector"><path d="M 0 88 C -10 38 22.5 50 12.5 0 " transform="translate(10.5,0.5)" pointer-events="visibleStroke" version="1.1" xmlns="http://www.w3.org/1999/xhtml" fill="none" stroke="#666" style=""></path><path pointer-events="all" version="1.1" xmlns="http://www.w3.org/1999/xhtml" d="M-1.7647200000000005,66.303232 L8.955147275230877,48.02525493465072 L0.9308726161701921,52.565190638595936 L-4.782894086173185,45.32966231848053 L-1.7647200000000005,66.303232" class="" stroke="#666" fill="#666" transform="translate(10.5,0.5)"></path><path pointer-events="all" version="1.1" xmlns="http://www.w3.org/1999/xhtml" d="M-1.7647200000000005,66.303232 L8.955147275230877,48.02525493465072 L0.9308726161701921,52.565190638595936 L-4.782894086173185,45.32966231848053 L-1.7647200000000005,66.303232" class="" stroke="#666" fill="#666" transform="translate(10.5,0.5)"></path></svg><div class="_jsPlumb_endpoint source-endpoint dependency-source-endpoint connected _jsPlumb_endpoint_anchor_ ui-draggable ui-droppable _jsPlumb_endpoint_connected" style="position: absolute; height: 20px; width: 20px; left: 274px; top: 543px;"><svg style="position:absolute;left:0px;top:0px" width="20" height="20" pointer-events="all" position="absolute" version="1.1" xmlns="http://www.w3.org/1999/xhtml"><circle cx="10" cy="10" r="10" version="1.1" xmlns="http://www.w3.org/1999/xhtml" fill="#666" stroke="none" style=""></circle></svg></div><div class="_jsPlumb_endpoint source-endpoint dependency-source-endpoint connected _jsPlumb_endpoint_anchor_ ui-draggable ui-droppable _jsPlumb_endpoint_connected" style="position: absolute; height: 20px; width: 20px; left: 266px; top: 671px;"><svg style="position:absolute;left:0px;top:0px" width="20" height="20" pointer-events="all" position="absolute" version="1.1" xmlns="http://www.w3.org/1999/xhtml"><circle cx="10" cy="10" r="10" version="1.1" xmlns="http://www.w3.org/1999/xhtml" fill="#666" stroke="none" style=""></circle></svg></div><div class="_jsPlumb_endpoint target-endpoint dependency-target-endpoint _jsPlumb_endpoint_anchor_ ui-draggable ui-droppable _jsPlumb_endpoint_connected" style="position: absolute; height: 20px; width: 20px; left: 266px; top: 631px;"><svg style="position:absolute;left:0px;top:0px" width="20" height="20" pointer-events="all" position="absolute" version="1.1" xmlns="http://www.w3.org/1999/xhtml"><circle cx="10" cy="10" r="10" version="1.1" xmlns="http://www.w3.org/1999/xhtml" fill="#666" stroke="none" style=""></circle></svg></div><div class="_jsPlumb_endpoint source-endpoint dependency-source-endpoint connected _jsPlumb_endpoint_anchor_ ui-draggable ui-droppable" style="position: absolute; height: 20px; width: 20px; left: 272px; top: 927px;"><svg style="position:absolute;left:0px;top:0px" width="20" height="20" pointer-events="all" position="absolute" version="1.1" xmlns="http://www.w3.org/1999/xhtml"><circle cx="10" cy="10" r="10" version="1.1" xmlns="http://www.w3.org/1999/xhtml" fill="#666" stroke="none" style=""></circle></svg></div><div class="_jsPlumb_endpoint target-endpoint dependency-target-endpoint _jsPlumb_endpoint_anchor_ ui-draggable ui-droppable _jsPlumb_endpoint_connected" style="position: absolute; height: 20px; width: 20px; left: 272px; top: 887px;"><svg style="position:absolute;left:0px;top:0px" width="20" height="20" pointer-events="all" position="absolute" version="1.1" xmlns="http://www.w3.org/1999/xhtml"><circle cx="10" cy="10" r="10" version="1.1" xmlns="http://www.w3.org/1999/xhtml" fill="#666" stroke="none" style=""></circle></svg></div><div class="_jsPlumb_endpoint source-endpoint dependency-source-endpoint connected _jsPlumb_endpoint_anchor_ ui-draggable ui-droppable _jsPlumb_endpoint_connected" style="position: absolute; height: 20px; width: 20px; left: 394.047px; top: 927.953px;"><svg style="position:absolute;left:0px;top:0px" width="20" height="20" pointer-events="all" position="absolute" version="1.1" xmlns="http://www.w3.org/1999/xhtml"><circle cx="10" cy="10" r="10" version="1.1" xmlns="http://www.w3.org/1999/xhtml" fill="#666" stroke="none" style=""></circle></svg></div><div class="_jsPlumb_endpoint target-endpoint dependency-target-endpoint _jsPlumb_endpoint_anchor_ ui-draggable ui-droppable _jsPlumb_endpoint_connected" style="position: absolute; height: 20px; width: 20px; left: 394.047px; top: 887.953px;"><svg style="position:absolute;left:0px;top:0px" width="20" height="20" pointer-events="all" position="absolute" version="1.1" xmlns="http://www.w3.org/1999/xhtml"><circle cx="10" cy="10" r="10" version="1.1" xmlns="http://www.w3.org/1999/xhtml" fill="#666" stroke="none" style=""></circle></svg></div><div class="_jsPlumb_endpoint source-endpoint dependency-source-endpoint connected _jsPlumb_endpoint_anchor_ ui-draggable ui-droppable" style="position: absolute; height: 20px; width: 20px; left: 398.5px; top: 1055px;"><svg style="position:absolute;left:0px;top:0px" width="20" height="20" pointer-events="all" position="absolute" version="1.1" xmlns="http://www.w3.org/1999/xhtml"><circle cx="10" cy="10" r="10" version="1.1" xmlns="http://www.w3.org/1999/xhtml" fill="#666" stroke="none" style=""></circle></svg></div><div class="_jsPlumb_endpoint target-endpoint dependency-target-endpoint _jsPlumb_endpoint_anchor_ ui-draggable ui-droppable _jsPlumb_endpoint_connected" style="position: absolute; height: 20px; width: 20px; left: 398.5px; top: 1015px;"><svg style="position:absolute;left:0px;top:0px" width="20" height="20" pointer-events="all" position="absolute" version="1.1" xmlns="http://www.w3.org/1999/xhtml"><circle cx="10" cy="10" r="10" version="1.1" xmlns="http://www.w3.org/1999/xhtml" fill="#666" stroke="none" style=""></circle></svg></div><div class="_jsPlumb_endpoint source-endpoint dependency-source-endpoint connected _jsPlumb_endpoint_anchor_ ui-draggable ui-droppable _jsPlumb_endpoint_connected" style="position: absolute; height: 20px; width: 20px; left: 406.5px; top: 671px;"><svg style="position:absolute;left:0px;top:0px" width="20" height="20" pointer-events="all" position="absolute" version="1.1" xmlns="http://www.w3.org/1999/xhtml"><circle cx="10" cy="10" r="10" version="1.1" xmlns="http://www.w3.org/1999/xhtml" fill="#666" stroke="none" style=""></circle></svg></div><div class="_jsPlumb_endpoint source-endpoint dependency-source-endpoint connected _jsPlumb_endpoint_anchor_ ui-draggable ui-droppable _jsPlumb_endpoint_connected" style="position: absolute; height: 20px; width: 20px; left: 394px; top: 799px;"><svg style="position:absolute;left:0px;top:0px" width="20" height="20" pointer-events="all" position="absolute" version="1.1" xmlns="http://www.w3.org/1999/xhtml"><circle cx="10" cy="10" r="10" version="1.1" xmlns="http://www.w3.org/1999/xhtml" fill="#666" stroke="none" style=""></circle></svg></div><div class="_jsPlumb_endpoint target-endpoint dependency-target-endpoint _jsPlumb_endpoint_anchor_ ui-draggable ui-droppable _jsPlumb_endpoint_connected" style="position: absolute; height: 20px; width: 20px; left: 394px; top: 759px;"><svg style="position:absolute;left:0px;top:0px" width="20" height="20" pointer-events="all" position="absolute" version="1.1" xmlns="http://www.w3.org/1999/xhtml"><circle cx="10" cy="10" r="10" version="1.1" xmlns="http://www.w3.org/1999/xhtml" fill="#666" stroke="none" style=""></circle></svg></div></div></div>
    </body>
</html>
 ]]>
    </visualization>
  </metadata>
</job>
