<?xml version="1.0" encoding="UTF-8" standalone="no"?>
<job xmlns="urn:proactive:jobdescriptor:3.14" xmlns:xsi="http://www.w3.org/2001/XMLSchema-instance" maxNumberOfExecution="2" name="Vehicle_Type_Using_Model_Explainability" onTaskError="continueJobExecution" priority="normal" tags="Big Data,Samples,Model explainability,Machine Learning,Analytics" projectName="1. Basic Machine Learning" xsi:schemaLocation="urn:proactive:jobdescriptor:3.14 http://www.activeeon.com/public_content/schemas/proactive/jobdescriptor/3.14/schedulerjob.xsd">
  <variables>
    <variable model="PA:LIST(.,$HOME/,$WORK/,$SCRATCH/)" name="WORK_DIR" value="." description="Working directory for the data space used to transfer files automatically between the workflow tasks." hidden="false" advanced="false"/>
    <variable advanced="true" description="Container platform used for executing the workflow tasks." group="Container Parameters" hidden="false" model="PA:LIST(no-container,docker,podman,singularity)" name="CONTAINER_PLATFORM" value="docker"/>
    <variable advanced="true" description="If True, it will activate the use of GPU for the workflow tasks on the selected container platform." group="Container Parameters" hidden="false" model="PA:Boolean" name="CONTAINER_GPU_ENABLED" value="False"/>
    <variable advanced="true" description="Name of the container image being used." group="Container Parameters" hidden="false" model="PA:LIST(,docker://activeeon/dlm3,docker://activeeon/cuda,docker://activeeon/cuda2,docker://activeeon/rapidsai,docker://activeeon/nvidia:rapidsai)" name="CONTAINER_IMAGE" value=""/>
  </variables>
  <description>
    <![CDATA[ Predict vehicle type, then apply ELI5 and Kernel Explainer to understand the model’s global behavior or specific predictions. ]]>
  </description>
  <genericInformation>
<info name="bucketName" value="ai-machine-learning-workflows"/>
<info name="workflow.icon" value="/automation-dashboard/styles/patterns/img/wf-icons/machine_learning.png"/>
<info name="Documentation" value="PAIO/PAIOUserGuide.html#_basic_ml"/>
<info name="group" value="public-objects"/>
</genericInformation>
  <taskFlow>
    <task fork="true" name="Model_Explainability" preciousResult="true">
      <description>
        <![CDATA[ Allow to understand the model’s global behavior or specific predictions. ]]>
      </description>
      <variables>
        <variable advanced="false" description="If False, the task will be ignored, it will not be executed." inherited="false" model="PA:Boolean" name="TASK_ENABLED" value="True"/>
        <variable advanced="false" description="Partial Dependence Plots show how a feature affects predictions." inherited="false" name="FEATURE_PARTIAL_PLOTS" value="distance_circularity, max_length_aspect_ratio, skewness_major_axis"/>
        <variable advanced="false" description="2D Partial Dependence Plots show predictions for any combination of two features." inherited="false" name="FEATURE_PARTIAL2D_PLOTS" value="distance_circularity, max_length_aspect_ratio"/>
        <variable advanced="false" description="Row of data to show." inherited="false" name="SHAP_ROW_SHOW" value="10"/>
      </variables>
      <genericInformation>
        <info name="task.icon" value="/automation-dashboard/styles/patterns/img/wf-icons/model-explainability.png"/>
        <info name="task.documentation" value="PAIO/PAIOUserGuide.html#_ml_explainability"/>
      </genericInformation>
      <depends>
        <task ref="Train_Model"/>
        <task ref="Split_Data"/>
      </depends>
      <forkEnvironment javaHome="/usr">
        <envScript>
          <script>
            <file language="groovy" url="${PA_CATALOG_REST_URL}/buckets/scripts/resources/fork_env_ai/raw"/>
          </script>
        </envScript>
      </forkEnvironment>
      <scriptExecutable>
        <script>
          <file language="cpython" url="${PA_CATALOG_REST_URL}/buckets/ai-machine-learning/resources/Model_Explainability_Script/raw"/>
        </script>
      </scriptExecutable>
      <controlFlow block="none"/>
      <metadata>
        <positionTop>
            549.25
        </positionTop>
        <positionLeft>
            343.125
        </positionLeft>
      </metadata>
    </task>
    <task fork="true" name="Random_Forest">
      <description>
        <![CDATA[ Random Forest is an algorithm for regression, classification and other tasks that operates by constructing a multitude of decision trees at training time. ]]>
      </description>
      <variables>
        <variable advanced="false" description="If False, the task will be ignored, it will not be executed." inherited="false" model="PA:Boolean" name="TASK_ENABLED" value="True"/>
        <variable advanced="false" description="A set of specific variables (usecase-related) that are used in the model training process." inherited="false" name="INPUT_VARIABLES" value="{}"/>
        <variable advanced="false" description="Type of the algorithm to be used." inherited="false" model="PA:LIST(Classification, Regression)" name="TYPE" value="Classification"/>
      </variables>
      <genericInformation>
        <info name="task.icon" value="/automation-dashboard/styles/patterns/img/wf-icons/ml_ensemble.png"/>
        <info name="task.documentation" value="PAIO/PAIOUserGuide.html#_random_forest"/>
      </genericInformation>
      <forkEnvironment javaHome="/usr">
        <envScript>
          <script>
            <file language="groovy" url="${PA_CATALOG_REST_URL}/buckets/scripts/resources/fork_env_ai/raw"/>
          </script>
        </envScript>
      </forkEnvironment>
      <scriptExecutable>
        <script>
          <file language="cpython" url="${PA_CATALOG_REST_URL}/buckets/ai-machine-learning/resources/Random_Forest_Script/raw"/>
        </script>
      </scriptExecutable>
      <controlFlow block="none"/>
      <metadata>
        <positionTop>
            293.25
        </positionTop>
        <positionLeft>
            301.125
        </positionLeft>
      </metadata>
    </task>
    <task fork="true" name="Split_Data" preciousResult="true">
      <description>
        <![CDATA[ Separate data into training and testing sets. ]]>
      </description>
      <variables>
        <variable advanced="false" description="If False, the task will be ignored, it will not be executed." inherited="false" model="PA:Boolean" name="TASK_ENABLED" value="True"/>
        <variable advanced="false" description="Float number within the range (0.0, 1.0), not including the values 0.0 and 1.0." inherited="false" name="TRAIN_SIZE" value="0.7"/>
      </variables>
      <genericInformation>
        <info name="task.icon" value="/automation-dashboard/styles/patterns/img/wf-icons/data-processing.png"/>
        <info name="task.documentation" value="PAIO/PAIOUserGuide.html#_split_data"/>
      </genericInformation>
      <depends>
        <task ref="Import_Data_And_Automate_Feature_Engineering"/>
      </depends>
      <forkEnvironment javaHome="/usr">
        <envScript>
          <script>
            <file language="groovy" url="${PA_CATALOG_REST_URL}/buckets/scripts/resources/fork_env_ai/raw"/>
          </script>
        </envScript>
      </forkEnvironment>
      <scriptExecutable>
        <script>
          <file language="cpython" url="${PA_CATALOG_REST_URL}/buckets/ai-machine-learning/resources/Split_Data_Script/raw"/>
        </script>
      </scriptExecutable>
      <controlFlow block="none"/>
      <metadata>
        <positionTop>
            293.25
        </positionTop>
        <positionLeft>
            479.375
        </positionLeft>
      </metadata>
    </task>
    <task fork="true" name="Train_Model">
      <description>
        <![CDATA[ Train a classification/clustering/anomaly detection model. ]]>
      </description>
      <variables>
        <variable advanced="false" description="If False, the task will be ignored, it will not be executed." inherited="false" model="PA:Boolean" name="TASK_ENABLED" value="True"/>
        <variable advanced="false" description="Number of splits you want to perform on the data." inherited="false" model="PA:Integer" name="N_SPLITS" value="5"/>
      </variables>
      <genericInformation>
        <info name="task.icon" value="/automation-dashboard/styles/patterns/img/wf-icons/train.png"/>
        <info name="task.documentation" value="PAIO/PAIOUserGuide.html#_train_model"/>
      </genericInformation>
      <depends>
        <task ref="Split_Data"/>
        <task ref="Random_Forest"/>
      </depends>
      <forkEnvironment javaHome="/usr">
        <envScript>
          <script>
            <file language="groovy" url="${PA_CATALOG_REST_URL}/buckets/scripts/resources/fork_env_ai/raw"/>
          </script>
        </envScript>
      </forkEnvironment>
      <pre>
        <script>
          <file language="groovy" url="${PA_CATALOG_REST_URL}/buckets/ai-auto-ml-optimization/resources/get_automl_token/raw"/>
        </script>
      </pre>
      <scriptExecutable>
        <script>
          <file language="cpython" url="${PA_CATALOG_REST_URL}/buckets/ai-machine-learning/resources/Train_Model_Script/raw"/>
        </script>
      </scriptExecutable>
      <controlFlow block="none"/>
      <metadata>
        <positionTop>
            421.25
        </positionTop>
        <positionLeft>
            306.125
        </positionLeft>
      </metadata>
    </task>
    <task fork="true" name="Predict_Model" preciousResult="true">
      <description>
        <![CDATA[ Generate predictions using a trained model. ]]>
      </description>
      <variables>
        <variable advanced="false" description="If False, the task will be ignored, it will not be executed." inherited="false" model="PA:Boolean" name="TASK_ENABLED" value="True"/>
      </variables>
      <genericInformation>
        <info name="task.icon" value="/automation-dashboard/styles/patterns/img/wf-icons/predict.png"/>
        <info name="task.documentation" value="PAIO/PAIOUserGuide.html#_predict_model"/>
      </genericInformation>
      <depends>
        <task ref="Train_Model"/>
        <task ref="Split_Data"/>
      </depends>
      <forkEnvironment javaHome="/usr">
        <envScript>
          <script>
            <file language="groovy" url="${PA_CATALOG_REST_URL}/buckets/scripts/resources/fork_env_ai/raw"/>
          </script>
        </envScript>
      </forkEnvironment>
      <scriptExecutable>
        <script>
          <file language="cpython" url="${PA_CATALOG_REST_URL}/buckets/ai-machine-learning/resources/Predict_Model_Script/raw"/>
        </script>
      </scriptExecutable>
      <controlFlow block="none"/>
      <metadata>
        <positionTop>
            549.25
        </positionTop>
        <positionLeft>
            499.375
        </positionLeft>
      </metadata>
    </task>
    <task fork="true" name="Preview_Results" preciousResult="true">
      <description>
        <![CDATA[ Preview the HTML results of the predictions. ]]>
      </description>
      <variables>
        <variable advanced="false" description="If False, the task will be ignored, it will not be executed." inherited="false" model="PA:Boolean" name="TASK_ENABLED" value="True"/>
        <variable advanced="false" description="Format of the output" inherited="false" model="PA:LIST(CSV,JSON,HTML)" name="OUTPUT_TYPE" value="HTML"/>
        <variable advanced="false" description="Maximum number of rows displayed in the output" inherited="false" model="PA:Integer" name="LIMIT_OUTPUT_VIEW" value="1000"/>
      </variables>
      <genericInformation>
        <info name="task.icon" value="/automation-dashboard/styles/patterns/img/wf-icons/preview_results.png"/>
        <info name="task.documentation" value="PAIO/PAIOUserGuide.html#_preview_results"/>
      </genericInformation>
      <depends>
        <task ref="Predict_Model"/>
      </depends>
      <forkEnvironment javaHome="/usr">
        <envScript>
          <script>
            <file language="groovy" url="${PA_CATALOG_REST_URL}/buckets/scripts/resources/fork_env_ai/raw"/>
          </script>
        </envScript>
      </forkEnvironment>
      <scriptExecutable>
        <script>
          <file language="cpython" url="${PA_CATALOG_REST_URL}/buckets/ai-machine-learning/resources/Preview_Results_Script/raw"/>
        </script>
      </scriptExecutable>
      <controlFlow block="none"/>
      <metadata>
        <positionTop>
            677.25
        </positionTop>
        <positionLeft>
            499.375
        </positionLeft>
      </metadata>
    </task>
    <task fork="true" name="Import_Data_And_Automate_Feature_Engineering" preciousResult="true">
      <description>
        <![CDATA[ Assist data scientists to successfully load and encode their categorical data. ]]>
      </description>
      <variables>
        <variable advanced="false" description="Method/protocol to import the data from the data source." hidden="false" inherited="false" model="PA:LIST(PA:URL,PA:URI,PA:USER_FILE,PA:GLOBAL_FILE)" name="IMPORT_FROM" value="PA:URL"/>
        <variable advanced="false" description="Path or name of the file that contains the dataset." group="" hidden="false" inherited="false" model="$IMPORT_FROM" name="FILE_PATH" value="https://s3.eu-west-2.amazonaws.com/activeeon-public/datasets/vehicle_silhouette_weka_dataset.csv"/>
        <variable advanced="false" description="Delimiter to use." group="" hidden="false" inherited="false" name="FILE_DELIMITER" value=","/>
        <variable advanced="false" description="Maximum number of rows to be displayed in the workflow results." hidden="false" inherited="false" model="PA:Integer" name="LIMIT_OUTPUT_VIEW" value="100"/>
      </variables>
      <genericInformation>
        <info name="task.icon" value="/automation-dashboard/styles/patterns/img/wf-icons/data-processing.png"/>
        <info name="task.documentation" value="PAIO/PAIOUserGuide.html#_import_data_and_automate_feature_engineering"/>
      </genericInformation>
      <inputFiles>
        <files accessMode="transferFromGlobalSpace" includes="data_type_identifier/*"/>
        <files accessMode="transferFromGlobalSpace" includes="templates/*"/>
      </inputFiles>
      <forkEnvironment javaHome="/usr">
        <envScript>
          <script>
            <file language="groovy" url="${PA_CATALOG_REST_URL}/buckets/scripts/resources/fork_env_ai/raw"/>
          </script>
        </envScript>
      </forkEnvironment>
      <scriptExecutable>
        <script>
          <file language="cpython" url="${PA_CATALOG_REST_URL}/buckets/ai-machine-learning/resources/Import_Data_And_Automate_Feature_Engineering_Script/raw"/>
        </script>
      </scriptExecutable>
      <controlFlow block="none"/>
      <metadata>
        <positionTop>
            166.25
        </positionTop>
        <positionLeft>
            479.375
        </positionLeft>
      </metadata>
    </task>
  </taskFlow>
  <metadata>
    <visualization>
      <![CDATA[ <html>
    <head>
    <link rel="stylesheet" href="/studio/styles/studio-standalone.css">
        <style>
        #workflow-designer {
            left:0 !important;
            top:0 !important;
            width:2476px;
            height:3328px;
            }
        </style>
    </head>
    <body>
    <div id="workflow-visualization-view"><div id="workflow-visualization" style="position:relative;top:-161.25px;left:-296.125px"><div class="task ui-draggable _jsPlumb_endpoint_anchor_" id="jsPlumb_1_166" style="top: 549.25px; left: 343.125px;"><a class="task-name" data-toggle="tooltip" data-placement="right" title="Allow to understand the model’s global behavior or specific predictions."><img src="/automation-dashboard/styles/patterns/img/wf-icons/model-explainability.png" width="20px">&nbsp;<span class="name">Model_Explainability</span></a></div><div class="task ui-draggable" id="jsPlumb_1_169" style="top: 293.25px; left: 301.125px;"><a class="task-name" data-toggle="tooltip" data-placement="right" title="Random Forest is an algorithm for regression, classification and other tasks that operates by constructing a multitude of decision trees at training time."><img src="/automation-dashboard/styles/patterns/img/wf-icons/ml_ensemble.png" width="20px">&nbsp;<span class="name">Random_Forest</span></a></div><div class="task ui-draggable _jsPlumb_endpoint_anchor_" id="jsPlumb_1_175" style="top: 293.25px; left: 479.375px;"><a class="task-name" data-toggle="tooltip" data-placement="right" title="Separate data into training and testing sets."><img src="/automation-dashboard/styles/patterns/img/wf-icons/data-processing.png" width="20px">&nbsp;<span class="name">Split_Data</span></a></div><div class="task ui-draggable _jsPlumb_endpoint_anchor_" id="jsPlumb_1_178" style="top: 421.25px; left: 306.125px;"><a class="task-name" data-toggle="tooltip" data-placement="right" title="Train a classification/clustering/anomaly detection model."><img src="/automation-dashboard/styles/patterns/img/wf-icons/train.png" width="20px">&nbsp;<span class="name">Train_Model</span></a></div><div class="task ui-draggable _jsPlumb_endpoint_anchor_" id="jsPlumb_1_181" style="top: 549.25px; left: 499.375px;"><a class="task-name" data-toggle="tooltip" data-placement="right" title="Generate predictions using a trained model."><img src="/automation-dashboard/styles/patterns/img/wf-icons/predict.png" width="20px">&nbsp;<span class="name">Predict_Model</span></a></div><div class="task ui-draggable _jsPlumb_endpoint_anchor_" id="jsPlumb_1_184" style="top: 677.25px; left: 499.375px;"><a class="task-name" data-toggle="tooltip" data-placement="right" title="Preview the HTML results of the predictions."><img src="/automation-dashboard/styles/patterns/img/wf-icons/preview_results.png" width="20px">&nbsp;<span class="name">Preview_Results</span></a></div><div class="task ui-draggable" id="jsPlumb_1_187" style="top: 166.25px; left: 479.375px;"><a class="task-name" data-toggle="tooltip" data-placement="right" title="Assist data scientists to successfully load and encode their categorical data."><img src="/automation-dashboard/styles/patterns/img/wf-icons/data-processing.png" width="20px">&nbsp;<span class="name">Import_Data_And_Automate_Feature_Engineering</span></a></div><svg style="position:absolute;left:345.5px;top:461.5px" width="71" height="89" pointer-events="none" position="absolute" version="1.1" xmlns="http://www.w3.org/1999/xhtml" class="_jsPlumb_connector"><path d="M 50 88 C 60 38 -10 50 0 0 " transform="translate(10.5,0.5)" pointer-events="visibleStroke" version="1.1" xmlns="http://www.w3.org/1999/xhtml" fill="none" stroke="#666" style=""></path><path pointer-events="all" version="1.1" xmlns="http://www.w3.org/1999/xhtml" d="M47.68,64.44800000000001 L41.41237124575627,44.206536866150785 L39.35349791023281,53.193251537724066 L30.157622783480328,52.533038955917974 L47.68,64.44800000000001" class="" stroke="#666" fill="#666" transform="translate(10.5,0.5)"></path><path pointer-events="all" version="1.1" xmlns="http://www.w3.org/1999/xhtml" d="M47.68,64.44800000000001 L41.41237124575627,44.206536866150785 L39.35349791023281,53.193251537724066 L30.157622783480328,52.533038955917974 L47.68,64.44800000000001" class="" stroke="#666" fill="#666" transform="translate(10.5,0.5)"></path></svg><svg style="position:absolute;left:395.5px;top:333.5px" width="145" height="217" pointer-events="none" position="absolute" version="1.1" xmlns="http://www.w3.org/1999/xhtml" class="_jsPlumb_connector"><path d="M 0 216 C -10 166 134 50 124 0 " transform="translate(10.5,0.5)" pointer-events="visibleStroke" version="1.1" xmlns="http://www.w3.org/1999/xhtml" fill="none" stroke="#666" style=""></path><path pointer-events="all" version="1.1" xmlns="http://www.w3.org/1999/xhtml" d="M18.017791999999996,165.93523199999998 L35.04888581876551,153.32801805970345 L25.886832764154306,154.3560179743384 L23.469671793103938,145.45897729554915 L18.017791999999996,165.93523199999998" class="" stroke="#666" fill="#666" transform="translate(10.5,0.5)"></path><path pointer-events="all" version="1.1" xmlns="http://www.w3.org/1999/xhtml" d="M18.017791999999996,165.93523199999998 L35.04888581876551,153.32801805970345 L25.886832764154306,154.3560179743384 L23.469671793103938,145.45897729554915 L18.017791999999996,165.93523199999998" class="" stroke="#666" fill="#666" transform="translate(10.5,0.5)"></path></svg><svg style="position:absolute;left:345.5px;top:333.5px" width="195" height="89" pointer-events="none" position="absolute" version="1.1" xmlns="http://www.w3.org/1999/xhtml" class="_jsPlumb_connector"><path d="M 0 88 C -10 38 184 50 174 0 " transform="translate(10.5,0.5)" pointer-events="visibleStroke" version="1.1" xmlns="http://www.w3.org/1999/xhtml" fill="none" stroke="#666" style=""></path><path pointer-events="all" version="1.1" xmlns="http://www.w3.org/1999/xhtml" d="M25.380099,59.788559500000005 L46.569714461918245,59.774538942402465 L38.59105293027294,55.1549112340862 L41.93606619600444,46.56358501212953 L25.380099,59.788559500000005" class="" stroke="#666" fill="#666" transform="translate(10.5,0.5)"></path><path pointer-events="all" version="1.1" xmlns="http://www.w3.org/1999/xhtml" d="M25.380099,59.788559500000005 L46.569714461918245,59.774538942402465 L38.59105293027294,55.1549112340862 L41.93606619600444,46.56358501212953 L25.380099,59.788559500000005" class="" stroke="#666" fill="#666" transform="translate(10.5,0.5)"></path></svg><svg style="position:absolute;left:344px;top:333.5px" width="22.5" height="89" pointer-events="none" position="absolute" version="1.1" xmlns="http://www.w3.org/1999/xhtml" class="_jsPlumb_connector "><path d="M 1.5 88 C 11.5 38 -10 50 0 0 " transform="translate(10.5,0.5)" pointer-events="visibleStroke" version="1.1" xmlns="http://www.w3.org/1999/xhtml" fill="none" stroke="#666" style=""></path><path pointer-events="all" version="1.1" xmlns="http://www.w3.org/1999/xhtml" d="M4.193578125,66.78168750000002 L10.22883008187672,46.46972713628781 L3.5238641657164487,52.79771513115072 L-3.755142286972582,47.139441095571364 L4.193578125,66.78168750000002" class="" stroke="#666" fill="#666" transform="translate(10.5,0.5)"></path><path pointer-events="all" version="1.1" xmlns="http://www.w3.org/1999/xhtml" d="M4.193578125,66.78168750000002 L10.22883008187672,46.46972713628781 L3.5238641657164487,52.79771513115072 L-3.755142286972582,47.139441095571364 L4.193578125,66.78168750000002" class="" stroke="#666" fill="#666" transform="translate(10.5,0.5)"></path></svg><svg style="position:absolute;left:345.5px;top:461.5px" width="215" height="89" pointer-events="none" position="absolute" version="1.1" xmlns="http://www.w3.org/1999/xhtml" class="_jsPlumb_connector"><path d="M 194 88 C 204 38 -10 50 0 0 " transform="translate(10.5,0.5)" pointer-events="visibleStroke" version="1.1" xmlns="http://www.w3.org/1999/xhtml" fill="none" stroke="#666" style=""></path><path pointer-events="all" version="1.1" xmlns="http://www.w3.org/1999/xhtml" d="M164.246848,59.394175999999995 L147.23624623845478,46.75932626958708 L150.881182595071,55.2277640804361 L143.0698343188909,60.12499167451608 L164.246848,59.394175999999995" class="" stroke="#666" fill="#666" transform="translate(10.5,0.5)"></path><path pointer-events="all" version="1.1" xmlns="http://www.w3.org/1999/xhtml" d="M164.246848,59.394175999999995 L147.23624623845478,46.75932626958708 L150.881182595071,55.2277640804361 L143.0698343188909,60.12499167451608 L164.246848,59.394175999999995" class="" stroke="#666" fill="#666" transform="translate(10.5,0.5)"></path></svg><svg style="position:absolute;left:519.5px;top:333.5px" width="41" height="217" pointer-events="none" position="absolute" version="1.1" xmlns="http://www.w3.org/1999/xhtml" class="_jsPlumb_connector "><path d="M 20 216 C 30 166 -10 50 0 0 " transform="translate(10.5,0.5)" pointer-events="visibleStroke" version="1.1" xmlns="http://www.w3.org/1999/xhtml" fill="none" stroke="#666" style=""></path><path pointer-events="all" version="1.1" xmlns="http://www.w3.org/1999/xhtml" d="M19.5543875,167.0637915 L23.892352578616862,146.32296077949366 L17.73262538731202,153.18282673508634 L10.011387813703198,148.14472289218162 L19.5543875,167.0637915" class="" stroke="#666" fill="#666" transform="translate(10.5,0.5)"></path><path pointer-events="all" version="1.1" xmlns="http://www.w3.org/1999/xhtml" d="M19.5543875,167.0637915 L23.892352578616862,146.32296077949366 L17.73262538731202,153.18282673508634 L10.011387813703198,148.14472289218162 L19.5543875,167.0637915" class="" stroke="#666" fill="#666" transform="translate(10.5,0.5)"></path></svg><svg style="position:absolute;left:539.5px;top:589.5px" width="25.5" height="89" pointer-events="none" position="absolute" version="1.1" xmlns="http://www.w3.org/1999/xhtml" class="_jsPlumb_connector"><path d="M 4.5 88 C 14.5 38 -10 50 0 0 " transform="translate(10.5,0.5)" pointer-events="visibleStroke" version="1.1" xmlns="http://www.w3.org/1999/xhtml" fill="none" stroke="#666" style=""></path><path pointer-events="all" version="1.1" xmlns="http://www.w3.org/1999/xhtml" d="M6.950109375,66.78168750000002 L12.19383263091469,46.25114034666338 L5.739082405354392,52.834163932040326 L-1.7536909370449987,47.46216731630898 L6.950109375,66.78168750000002" class="" stroke="#666" fill="#666" transform="translate(10.5,0.5)"></path><path pointer-events="all" version="1.1" xmlns="http://www.w3.org/1999/xhtml" d="M6.950109375,66.78168750000002 L12.19383263091469,46.25114034666338 L5.739082405354392,52.834163932040326 L-1.7536909370449987,47.46216731630898 L6.950109375,66.78168750000002" class="" stroke="#666" fill="#666" transform="translate(10.5,0.5)"></path></svg><div class="_jsPlumb_endpoint source-endpoint dependency-source-endpoint connected _jsPlumb_endpoint_anchor_ ui-draggable ui-droppable" style="position: absolute; height: 20px; width: 20px; left: 396px; top: 580px;"><svg style="position:absolute;left:0px;top:0px" width="20" height="20" pointer-events="all" position="absolute" version="1.1" xmlns="http://www.w3.org/1999/xhtml"><circle cx="10" cy="10" r="10" version="1.1" xmlns="http://www.w3.org/1999/xhtml" fill="#666" stroke="none" style=""></circle></svg></div><div class="_jsPlumb_endpoint target-endpoint dependency-target-endpoint _jsPlumb_endpoint_anchor_ ui-draggable ui-droppable _jsPlumb_endpoint_connected" style="position: absolute; height: 20px; width: 20px; left: 396px; top: 540px;"><svg style="position:absolute;left:0px;top:0px" width="20" height="20" pointer-events="all" position="absolute" version="1.1" xmlns="http://www.w3.org/1999/xhtml"><circle cx="10" cy="10" r="10" version="1.1" xmlns="http://www.w3.org/1999/xhtml" fill="#666" stroke="none" style=""></circle></svg></div><div class="_jsPlumb_endpoint source-endpoint dependency-source-endpoint connected _jsPlumb_endpoint_anchor_ ui-draggable ui-droppable _jsPlumb_endpoint_connected" style="position: absolute; height: 20px; width: 20px; left: 344.5px; top: 324px;"><svg style="position:absolute;left:0px;top:0px" width="20" height="20" pointer-events="all" position="absolute" version="1.1" xmlns="http://www.w3.org/1999/xhtml"><circle cx="10" cy="10" r="10" version="1.1" xmlns="http://www.w3.org/1999/xhtml" fill="#666" stroke="none" style=""></circle></svg></div><div class="_jsPlumb_endpoint source-endpoint dependency-source-endpoint connected _jsPlumb_endpoint_anchor_ ui-draggable ui-droppable _jsPlumb_endpoint_connected" style="position: absolute; height: 20px; width: 20px; left: 520px; top: 324px;"><svg style="position:absolute;left:0px;top:0px" width="20" height="20" pointer-events="all" position="absolute" version="1.1" xmlns="http://www.w3.org/1999/xhtml"><circle cx="10" cy="10" r="10" version="1.1" xmlns="http://www.w3.org/1999/xhtml" fill="#666" stroke="none" style=""></circle></svg></div><div class="_jsPlumb_endpoint target-endpoint dependency-target-endpoint _jsPlumb_endpoint_anchor_ ui-draggable ui-droppable _jsPlumb_endpoint_connected connected" style="position: absolute; height: 20px; width: 20px; left: 520px; top: 284px;"><svg style="position:absolute;left:0px;top:0px" width="20" height="20" pointer-events="all" position="absolute" version="1.1" xmlns="http://www.w3.org/1999/xhtml"><circle cx="10" cy="10" r="10" version="1.1" xmlns="http://www.w3.org/1999/xhtml" fill="#666" stroke="none" style=""></circle></svg></div><div class="_jsPlumb_endpoint source-endpoint dependency-source-endpoint connected _jsPlumb_endpoint_anchor_ ui-draggable ui-droppable _jsPlumb_endpoint_connected" style="position: absolute; height: 20px; width: 20px; left: 346px; top: 452px;"><svg style="position:absolute;left:0px;top:0px" width="20" height="20" pointer-events="all" position="absolute" version="1.1" xmlns="http://www.w3.org/1999/xhtml"><circle cx="10" cy="10" r="10" version="1.1" xmlns="http://www.w3.org/1999/xhtml" fill="#666" stroke="none" style=""></circle></svg></div><div class="_jsPlumb_endpoint target-endpoint dependency-target-endpoint _jsPlumb_endpoint_anchor_ ui-draggable ui-droppable _jsPlumb_endpoint_connected" style="position: absolute; height: 20px; width: 20px; left: 346px; top: 412px;"><svg style="position:absolute;left:0px;top:0px" width="20" height="20" pointer-events="all" position="absolute" version="1.1" xmlns="http://www.w3.org/1999/xhtml"><circle cx="10" cy="10" r="10" version="1.1" xmlns="http://www.w3.org/1999/xhtml" fill="#666" stroke="none" style=""></circle></svg></div><div class="_jsPlumb_endpoint source-endpoint dependency-source-endpoint connected _jsPlumb_endpoint_anchor_ ui-draggable ui-droppable _jsPlumb_endpoint_connected" style="position: absolute; height: 20px; width: 20px; left: 540px; top: 580px;"><svg style="position:absolute;left:0px;top:0px" width="20" height="20" pointer-events="all" position="absolute" version="1.1" xmlns="http://www.w3.org/1999/xhtml"><circle cx="10" cy="10" r="10" version="1.1" xmlns="http://www.w3.org/1999/xhtml" fill="#666" stroke="none" style=""></circle></svg></div><div class="_jsPlumb_endpoint target-endpoint dependency-target-endpoint _jsPlumb_endpoint_anchor_ ui-draggable ui-droppable _jsPlumb_endpoint_connected" style="position: absolute; height: 20px; width: 20px; left: 540px; top: 540px;"><svg style="position:absolute;left:0px;top:0px" width="20" height="20" pointer-events="all" position="absolute" version="1.1" xmlns="http://www.w3.org/1999/xhtml"><circle cx="10" cy="10" r="10" version="1.1" xmlns="http://www.w3.org/1999/xhtml" fill="#666" stroke="none" style=""></circle></svg></div><div class="_jsPlumb_endpoint source-endpoint dependency-source-endpoint connected _jsPlumb_endpoint_anchor_ ui-draggable ui-droppable" style="position: absolute; height: 20px; width: 20px; left: 544.5px; top: 708px;"><svg style="position:absolute;left:0px;top:0px" width="20" height="20" pointer-events="all" position="absolute" version="1.1" xmlns="http://www.w3.org/1999/xhtml"><circle cx="10" cy="10" r="10" version="1.1" xmlns="http://www.w3.org/1999/xhtml" fill="#666" stroke="none" style=""></circle></svg></div><div class="_jsPlumb_endpoint target-endpoint dependency-target-endpoint _jsPlumb_endpoint_anchor_ ui-draggable ui-droppable _jsPlumb_endpoint_connected" style="position: absolute; height: 20px; width: 20px; left: 544.5px; top: 668px;"><svg style="position:absolute;left:0px;top:0px" width="20" height="20" pointer-events="all" position="absolute" version="1.1" xmlns="http://www.w3.org/1999/xhtml"><circle cx="10" cy="10" r="10" version="1.1" xmlns="http://www.w3.org/1999/xhtml" fill="#666" stroke="none" style=""></circle></svg></div><div class="_jsPlumb_endpoint source-endpoint dependency-source-endpoint connected _jsPlumb_endpoint_anchor_ ui-draggable ui-droppable endpointDrag _jsPlumb_endpoint_connected" style="position: absolute; height: 20px; width: 20px; left: 601.5px; top: 197px; visibility: visible;" dragid="jsPlumb_1_209" elid="jsPlumb_1_187"><svg style="position:absolute;left:0px;top:0px" width="20" height="20" pointer-events="all" position="absolute" version="1.1" xmlns="http://www.w3.org/1999/xhtml"><circle cx="10" cy="10" r="10" version="1.1" xmlns="http://www.w3.org/1999/xhtml" fill="#666" stroke="none" style=""></circle></svg></div><svg style="position:absolute;left:519.5px;top:206.5px" width="102.5" height="88" pointer-events="none" position="absolute" version="1.1" xmlns="http://www.w3.org/1999/xhtml" class="_jsPlumb_connector"><path d="M 0 87 C -10 37 91.5 50 81.5 0 " transform="translate(10.5,0.5)" pointer-events="visibleStroke" version="1.1" xmlns="http://www.w3.org/1999/xhtml" fill="none" stroke="#666" style=""></path><path pointer-events="all" version="1.1" xmlns="http://www.w3.org/1999/xhtml" d="M7.215295999999998,61.805952 L27.258115768021522,54.92951573209163 L18.213288830269498,53.14314912186981 L18.595312889891336,43.93152290182212 L7.215295999999998,61.805952" class="" stroke="#666" fill="#666" transform="translate(10.5,0.5)"></path></svg></div></div>
    </body>
</html>
 ]]>
    </visualization>
  </metadata>
</job>
