<?xml version="1.0" encoding="UTF-8"?>
<job
        xmlns:xsi="http://www.w3.org/2001/XMLSchema-instance"
        xmlns="urn:proactive:jobdescriptor:3.13" xsi:schemaLocation="urn:proactive:jobdescriptor:3.13 http://www.activeeon.com/public_content/schemas/proactive/jobdescriptor/3.13/schedulerjob.xsd"  name="YARN_Pi" projectName="1. Basic MapReduce Examples" priority="normal" onTaskError="continueJobExecution"  maxNumberOfExecution="2"  >
    <variables>
        <variable name="nb_maps" value="16" model=""/>
        <variable name="nb_samples" value="10000" model=""/>
        <variable name="yarn_service_instance_id" value="xx"  model="PA:NOT_EMPTY_STRING"/>
    </variables>
    <description>
        <![CDATA[ A workflow to submit a YARN MapReduce job from a docker container, to estimate Pi. This workflow requires to start the PaaS Service Docker_Swarm, HDFS and YARN before. Set the YARN_service_instance_id parameter to the running YARN service instance id. ]]>
    </description>
    <genericInformation>
        <info name="bucketName" value="big-data"/>
        <info name="workflow.icon" value="/automation-dashboard/styles/patterns/img/wf-icons/yarn.png"/>
        <info name="group" value="public-objects"/>
    </genericInformation>
    <taskFlow>

        <task name="retrieve_service_variables"
              fork="true">
            <scriptExecutable>
                <script>
                    <file url="${PA_CATALOG_REST_URL}/buckets/service-automation/resources/Retrieve_variables_from_service_instance_id/raw" language="groovy">
                        <arguments>
                            <argument value="$yarn_service_instance_id"/>
                            <argument value="targeted_network_name"/>
                            <argument value="targeted_network_name"/>
                            <argument value="yarn_master_container_name"/>
                            <argument value="yarn_master_container_name"/>
                            <argument value="hdfs_namenode_container_name"/>
                            <argument value="hdfs_namenode_container_name"/>
                            <argument value="yarn_token_name"/>
                            <argument value="INSTANCE_NAME"/>
                        </arguments>
                    </file>
                </script>
            </scriptExecutable>
        </task>


        <task name="YARN_Pi"
              fork="true">
            <description>
                <![CDATA[ A YARN MapReduce task to estimate Pi. ]]>
            </description>
            <genericInformation>
                <info name="task.icon" value="/automation-dashboard/styles/patterns/img/wf-icons/yarn.png"/>
                <info name="NODE_ACCESS_TOKEN" value="$yarn_token_name"/>
            </genericInformation>
            <depends>
                <task ref="retrieve_service_variables"/>
            </depends>

            <scriptExecutable>
                <script>
                    <code language="groovy">
                        <![CDATA[
// Retrieve variables
def targeted_network_name = variables.get("targeted_network_name")
def yarn_master_container_name = variables.get("yarn_master_container_name")
def hdfs_namenode_container_name = variables.get("hdfs_namenode_container_name")
def nb_maps = variables.get("nb_maps")
def nb_samples = variables.get("nb_samples")


// yarn container configuration
def hdfs_core_site_config_command = "sed -i 's/toreplace:port/" + hdfs_namenode_container_name + ":9000" + "/g' \$HADOOP_HOME/etc/hadoop/core-site.xml"
def hdfs_hdfs_site_config = "sed -i 's/toreplace/" + hdfs_namenode_container_name + "/g' \$HADOOP_HOME/etc/hadoop/hdfs-site.xml"
def yarn_mapred_site_config = "sed -i 's/toreplace/" + yarn_master_container_name + "/g' \$HADOOP_HOME/etc/hadoop/mapred-site.xml"
def yarn_yarn_site_config = "sed -i 's/toreplace/" + yarn_master_container_name + "/g' \$HADOOP_HOME/etc/hadoop/yarn-site.xml"
def command_in_container = hdfs_core_site_config_command + ";" + hdfs_hdfs_site_config + ";" + yarn_mapred_site_config + ";" + yarn_yarn_site_config + ";"


// Submit the Yarn pi job
def yarn_shell_command = command_in_container + "yarn jar /usr/local/hadoop/share/hadoop/mapreduce/hadoop-mapreduce-examples-2.7.0.jar pi " + nb_maps + " " + nb_samples
cmd = ["docker", "run", "--rm", "--net", targeted_network_name, "activeeon/yarn:latest", "bash", "-c", yarn_shell_command]
println cmd

cmd.execute().waitForProcessOutput(System.out, System.err)
]]>
                    </code>
                </script>
            </scriptExecutable>
            <metadata>
                <positionTop>
                    308.125
                </positionTop>
                <positionLeft>
                    514
                </positionLeft>
            </metadata>
        </task>
    </taskFlow>
    <metadata>
        <visualization>
            <![CDATA[ <html>
    <head>
    <link rel="stylesheet" href="/studio/styles/studio-standalone.css">
        <style>
        #workflow-designer {
            left:0 !important;
            top:0 !important;
            width:2830px;
            height:3392px;
            }
        </style>
    </head>
    <body>
    <div id="workflow-visualization-view"><div id="workflow-visualization" style="position:relative;top:-303.125px;left:-509px"><div class="task _jsPlumb_endpoint_anchor_ ui-draggable active-task" id="jsPlumb_1_49" style="top: 308.133px; left: 514px;"><a class="task-name" data-toggle="tooltip" data-placement="right" title="A workflow to submit a yarn job from a docker container, to estimate Pi. This workflow requires a yarn platform."><img src="/automation-dashboard/styles/patterns/img/wf-icons/yarn.png" width="20px">&nbsp;<span class="name">yarn_Pi</span></a></div><div class="_jsPlumb_endpoint source-endpoint dependency-source-endpoint connected _jsPlumb_endpoint_anchor_ ui-draggable ui-droppable" style="position: absolute; height: 20px; width: 20px; left: 554px; top: 338px;"><svg style="position:absolute;left:0px;top:0px" width="20" height="20" pointer-events="all" position="absolute" version="1.1" xmlns="http://www.w3.org/1999/xhtml"><circle cx="10" cy="10" r="10" version="1.1" xmlns="http://www.w3.org/1999/xhtml" fill="#666" stroke="none" style=""></circle></svg></div></div></div>
    </body>
</html>
 ]]>
        </visualization>
    </metadata>
</job>
